seafile_mirror/__init__.py
seafile_mirror/_cachedb.py
seafile_mirror/_helpers.py
seafile_mirror/_seafile.py
seafile_mirror/seafile_mirror.py
seafile_mirror-0.2.2.dist-info/LICENSES/Apache-2.0.txt
seafile_mirror-0.2.2.dist-info/METADATA
seafile_mirror-0.2.2.dist-info/WHEEL
seafile_mirror-0.2.2.dist-info/entry_points.txt
seafile_mirror-0.2.2.dist-info/RECORD
