Metadata-Version: 2.3
Name: seafile-mirror
Version: 0.2.2
Summary: Handle clean read-only (re-)syncs of Seafile libraries to mirror them
License: Apache-2.0
Author: Max Mehl
Author-email: mail@mehl.mx
Requires-Python: >=3.10,<4.0
Classifier: License :: OSI Approved :: Apache Software License
Classifier: Programming Language :: Python :: 3
Classifier: Programming Language :: Python :: 3.10
Classifier: Programming Language :: Python :: 3.11
Classifier: Programming Language :: Python :: 3.12
Classifier: Programming Language :: Python :: 3.13
Requires-Dist: pyyaml (>=6.0.1,<7.0.0)
Project-URL: Repository, https://src.mehl.mx/mxmehl/seafile-mirror
